setup.py
qgen/__init__.py
qgen/__main__.py
qgen/build_helpers.py
qgen/built_in_functions.py
qgen/qgen.py
qgen/qgen_exceptions.py
qgen.egg-info/PKG-INFO
qgen.egg-info/SOURCES.txt
qgen.egg-info/dependency_links.txt
qgen.egg-info/top_level.txt
qgen/generators/__init__.py
qgen/generators/generate_moodle_xml.py
qgen/generators/moodle_xml_builder.py