Metadata-Version: 1.0
Name: qgen
Version: 1.3
Summary: Question generating framework
Home-page: https://github.com/JA-VON/QGenPY
Author: Javon Davis, Howard Edwards, Alexander Nicholson
Author-email: javonldavis14@gmail.com, howarde.jr@hotmail.com, alexj.nich@hotmail.com
License: MIT
Platform: UNKNOWN
